{"cameraMode":{"drawMode":0,"name":"Shaded","section":"Shading Mode"},"sceneLighting":true,"audioPlay":false,"sceneViewState":{"m_AlwaysRefresh":false,"showFog":true,"showSkybox":true,"showFlares":true,"showImageEffects":true,"showParticleSystems":true,"showVisualEffectGraphs":true,"m_FxEnabled":true},"in2DMode":false,"pivot":{"x":5.146475791931152,"y":7.937071800231934,"z":7.123401641845703},"rotation":{"x":-0.05479256063699722,"y":0.2044144570827484,"z":-0.010578171350061894,"w":-0.9775741696357727},"size":16.22852897644043,"orthographic":false}